LICENSE
MANIFEST.in
README.md
setup.py
pycaps/__init__.py
pycaps/caps.py
pycaps.egg-info/PKG-INFO
pycaps.egg-info/SOURCES.txt
pycaps.egg-info/dependency_links.txt
pycaps.egg-info/not-zip-safe
pycaps.egg-info/top_level.txt